cv_plot/__init__.py
cv_plot/core/__init__.py
cv_plot/core/axes.py
cv_plot/core/drawable.py
cv_plot/core/projection.py
cv_plot/core/transformation.py
cv_plot/core/util.py
cv_plot/drawables/__init__.py
cv_plot/drawables/axis.py
cv_plot/drawables/border.py
cv_plot/drawables/grid.py
cv_plot/drawables/group.py
cv_plot/drawables/image.py
cv_plot/drawables/label.py
cv_plot/drawables/legend.py
cv_plot/drawables/line.py
cv_plot/plot.py
opencv_cv_plot-0.5.0.dist-info/WHEEL
opencv_cv_plot-0.5.0.dist-info/METADATA
opencv_cv_plot-0.5.0.dist-info/RECORD
