Metadata-Version: 2.3
Name: opencv-cv-plot
Version: 0.5.0
Summary: A plot library using pure opencv.
Author: Dominik Wetzel
Author-email: Dominik Wetzel <dimonok@web.de>
License: MIT License
Classifier: Development Status :: 3 - Alpha
Classifier: License :: OSI Approved :: MIT License
Classifier: Programming Language :: Python :: 3
Classifier: Programming Language :: Python :: 3.9
Classifier: Programming Language :: Python :: 3.10
Classifier: Programming Language :: Python :: 3.11
Classifier: Programming Language :: Python :: 3.12
Classifier: Programming Language :: Python :: 3.13
Classifier: Intended Audience :: Developers
Classifier: Operating System :: OS Independent
Classifier: Topic :: Scientific/Engineering :: Image Processing
Classifier: Topic :: Scientific/Engineering :: Visualization
Classifier: Topic :: Software Development :: Libraries :: Python Modules
Requires-Dist: opencv-python>=4
Requires-Python: >=3.9
Project-URL: Homepage, https://github.com/Schmetzler/cv-plot-python
Project-URL: Repository, https://github.com/Schmetzler/cv-plot-python.git
